qapp_pyquil/__init__.py
qapp_pyquil/async_tasks/__init__.py
qapp_pyquil/async_tasks/pyquil_circuit_export_task.py
qapp_pyquil/component/__init__.py
qapp_pyquil/component/backend/__init__.py
qapp_pyquil/component/backend/pyquil_invocation.py
qapp_pyquil/factory/__init__.py
qapp_pyquil/factory/pyquil_device_factory.py
qapp_pyquil/factory/pyquil_handler_factory.py
qapp_pyquil/factory/pyquil_provider_factory.py
qapp_pyquil/handler/__init__.py
qapp_pyquil/handler/invocation_handler.py
qapp_pyquil/model/__init__.py
qapp_pyquil/model/device/__init__.py
qapp_pyquil/model/device/qapp_pyquil_device.py
qapp_pyquil/model/provider/__init__.py
qapp_pyquil/model/provider/qapp_pyquil_provider.py
qapp_pyquil-0.0.1.dist-info/LICENSE
qapp_pyquil-0.0.1.dist-info/METADATA
qapp_pyquil-0.0.1.dist-info/WHEEL
qapp_pyquil-0.0.1.dist-info/top_level.txt
qapp_pyquil-0.0.1.dist-info/RECORD
